suhteita/__init__.py
suhteita/__main__.py
suhteita/cli.py
suhteita/source_server_actions.py
suhteita/store.py
suhteita/suhteita.py
suhteita/ticket_system_actions.py
suhteita/robot/__init__.py
suhteita/robot/TicketSystemLibrary/__init__.py
suhteita/robot/TicketSystemLibrary/ticket_system_bridge.py
suhteita-2025.5.3.dist-info/licenses/LICENSE
suhteita-2025.5.3.dist-info/METADATA
suhteita-2025.5.3.dist-info/WHEEL
suhteita-2025.5.3.dist-info/entry_points.txt
suhteita-2025.5.3.dist-info/top_level.txt
suhteita-2025.5.3.dist-info/RECORD
