Metadata-Version: 2.4
Name: suhteita
Version: 2025.5.3
Summary: Relationships (Finnish: suhteita) maintained across distances as load test core.
Author-email: Stefan Hagen <stefan@hagen.link>
Maintainer-email: Stefan Hagen <stefan@hagen.link>
License: MIT License
Project-URL: Homepage, https://git.sr.ht/~sthagen/suhteita
Project-URL: Bug-Tracker, https://todo.sr.ht/~sthagen/suhteita
Project-URL: Documentation, https://codes.dilettant.life/docs/suhteita
Project-URL: Source-Code, https://git.sr.ht/~sthagen/suhteita
Project-URL: Test-Coverage, https://codes.dilettant.life/coverage/suhteita
Keywords: developer-tools,validation,verification
Classifier: Development Status :: 3 - Alpha
Classifier: Intended Audience :: Developers
Classifier: License :: OSI Approved :: MIT License
Classifier: Programming Language :: Python :: 3.10
Classifier: Programming Language :: Python :: 3.11
Classifier: Programming Language :: Python :: 3.12
Classifier: Programming Language :: Python :: 3.13
Classifier: Programming Language :: Python :: 3.9
Requires-Python: >=3.9
License-File: LICENSE
Requires-Dist: atlassian-python-api>=3.41.3
Requires-Dist: jmespath>=1.0.1
Requires-Dist: robotframework>=6.1.1
Requires-Dist: wrapt>=1.16.0
Requires-Dist: tomli; python_version < "3.11"
Provides-Extra: dev
Requires-Dist: black; extra == "dev"
Requires-Dist: coverage; extra == "dev"
Requires-Dist: hypothesis; extra == "dev"
Requires-Dist: mypy; extra == "dev"
Requires-Dist: pytest; extra == "dev"
Requires-Dist: pytest-cov; extra == "dev"
Requires-Dist: pytest-flake8; extra == "dev"
Requires-Dist: ruff; extra == "dev"
Requires-Dist: types-jmespath; extra == "dev"
Dynamic: license-file
